score.es6-0.0.3-py3.4-nspkg.pth
score/es6/__init__.py
score/es6/_init.py
score/es6/ctx.py
score/es6/dsl.py
score.es6-0.0.3.dist-info/DESCRIPTION.rst
score.es6-0.0.3.dist-info/METADATA
score.es6-0.0.3.dist-info/RECORD
score.es6-0.0.3.dist-info/WHEEL
score.es6-0.0.3.dist-info/metadata.json
score.es6-0.0.3.dist-info/namespace_packages.txt
score.es6-0.0.3.dist-info/top_level.txt
